{"total":18,"pageSize":10,"pageCount":2,"current":1,"data":[{"title":"Javascript: Class(2)","date":"2018-08-31T15:15:49.000Z","excerpt":"","slug":"js-class-2","tags":["note","javascript"],"categories":["language core"]},{"title":"Web Worker","date":"2018-08-26T11:13:27.000Z","excerpt":"","slug":"web-worker","tags":["note side"]},{"title":"Javascript: Class (1)","date":"2018-08-17T15:17:16.000Z","excerpt":"","slug":"js-class-1","tags":["note","javascript"],"categories":["language core"]},{"title":"Javascript: Functions","date":"2018-08-10T13:17:23.000Z","excerpt":"","slug":"js-functions","tags":["note","javascript"],"categories":["language core"]},{"title":"Javascript: Array","date":"2018-08-04T01:53:47.000Z","excerpt":"","slug":"JS-array","tags":["note","javascript"],"categories":["language core"]},{"title":"Javascript: Objects","date":"2018-07-27T14:31:56.000Z","excerpt":"","slug":"javascript-objects","tags":["note","javascript"],"categories":["language core"]},{"title":"Javascript: Statements","date":"2018-07-19T12:18:23.000Z","excerpt":"","slug":"JS-statements","tags":["note","javascript"],"categories":["language core"]},{"title":"Javascript: expression and operator","date":"2018-07-14T03:29:21.000Z","excerpt":"","slug":"javascript-expression-operator","tags":["note","javascript"],"categories":["language core"]},{"title":"Javascript: Objects and variable Intro","date":"2018-07-02T14:54:01.000Z","excerpt":"","slug":"javascript-objects-variable-intro","tags":["note","javascript"],"categories":["language core"]},{"title":"Python: Introducing python object types","date":"2018-07-02T14:52:03.000Z","excerpt":"","slug":"introducing-python-object-types","tags":["python","note"],"categories":["language core"]}]}